pyQIS/__init__.py
pyQIS/data.py
pyQIS-0.0.3.dist-info/LICENSE
pyQIS-0.0.3.dist-info/METADATA
pyQIS-0.0.3.dist-info/WHEEL
pyQIS-0.0.3.dist-info/top_level.txt
pyQIS-0.0.3.dist-info/RECORD
