Metadata-Version: 2.1
Name: pyQIS
Version: 0.0.3
Summary: QIS client for German university information servers.
Home-page: https://gitlab.com/Scrumplex/pyqis
Author: Sefa Eyeoglu
Author-email: contact@scrumplex.net
License: GPL3
Keywords: pyQIS client library university grade results
Platform: UNKNOWN
Classifier: Development Status :: 3 - Alpha
Classifier: Topic :: Internet
Classifier: License :: OSI Approved :: GNU General Public License v3 (GPLv3)
Requires-Dist: requests
Requires-Dist: beautifulsoup4
Requires-Dist: lxml
